mycalc/calculator.py
2024OSS_PyPi_dinogarlic-0.0.1.dist-info/LICENSE
2024OSS_PyPi_dinogarlic-0.0.1.dist-info/METADATA
2024OSS_PyPi_dinogarlic-0.0.1.dist-info/WHEEL
2024OSS_PyPi_dinogarlic-0.0.1.dist-info/top_level.txt
2024OSS_PyPi_dinogarlic-0.0.1.dist-info/RECORD
