Metadata-Version: 2.1
Name: 2024OSS-PyPi-dinogarlic
Version: 0.0.1
Summary: nice calculator
Home-page: https://github.com/Dinogarlic/oss-world
Download-URL: https://github.com/Dinogarlic/oss-world
Author: dinogarlic
Classifier: Programming Language :: Python :: 3
License-File: LICENSE
